python_textbelt/__init__.py
python_textbelt/exceptions.py
python_textbelt/textbelt.py
python_textbelt-0.0.1.dist-info/METADATA
python_textbelt-0.0.1.dist-info/WHEEL
python_textbelt-0.0.1.dist-info/licenses/LICENSE
python_textbelt-0.0.1.dist-info/RECORD
